[
    {
        "name": "John Doe",
        "dob": "1980-05-15",
        "gender": "male",
        "age": 43
    },
    {
        "name": "Jane Smith",
        "dob": "1995-08-22",
        "gender": "female",
        "age": 28
    },
    {
        "name": "Alice Johnson",
        "dob": "1975-11-30",
        "gender": "female",
        "age": 48
    },
    {
        "name": "Bob Brown",
        "dob": "2005-02-14",
        "gender": "male",
        "age": 18
    },
    {
        "name": "Charlie Davis",
        "dob": "1960-07-19",
        "gender": "male",
        "age": 63
    },
    {
        "name": "Diana Evans",
        "dob": "1988-03-25",
        "gender": "female",
        "age": 35
    },
    {
        "name": "Ethan Harris",
        "dob": "1999-12-10",
        "gender": "male",
        "age": 23
    },
    {
        "name": "Fiona Clark",
        "dob": "1970-09-05",
        "gender": "female",
        "age": 53
    },
    {
        "name": "George Lewis",
        "dob": "1983-06-18",
        "gender": "male",
        "age": 40
    },
    {
        "name": "Hannah Walker",
        "dob": "2007-01-01",
        "gender": "female",
        "age": 16
    }
]